caco/__init__.py
caco/__main__.py
caco/caco.yml
caco/caco_cli.py
caco/library_cc.py
caco/main_cc.py
caco/test.py
caco/threshold_minimum.py
caco-0.2.4.dist-info/DESCRIPTION.rst
caco-0.2.4.dist-info/METADATA
caco-0.2.4.dist-info/RECORD
caco-0.2.4.dist-info/WHEEL
caco-0.2.4.dist-info/entry_points.txt
caco-0.2.4.dist-info/metadata.json
caco-0.2.4.dist-info/top_level.txt
