Metadata-Version: 2.0
Name: caco
Version: 0.2.4
Summary: Estimation of canopy attributes from digital cover photography
Home-page: https://github.com/alivernini/caco
Author: Alessandro Alivernini
Author-email: alessandro.alivernini@crea.gov.it
License: MIT
Download-URL: https://github.com/alivernini/caco/archive/v0.2.5.tar.gz
Keywords: tree,canopy,gap fraction,lai,leaf area index
Platform: UNKNOWN
Classifier: Development Status :: 3 - Alpha
Classifier: License :: OSI Approved :: MIT License
Classifier: Programming Language :: Python :: 2.7
Classifier: Programming Language :: Python :: 3.4
Classifier: Programming Language :: Python :: 3.5
Requires-Dist: PyYAML (>=3.12)
Requires-Dist: numpy (>=1.11.0)
Requires-Dist: pandas (>=0.20.1)
Requires-Dist: rawpy (>=0.10.1)
Requires-Dist: scikit-image (>=0.13.1)
Requires-Dist: scipy (>=0.19.1)
Requires-Dist: xlwt (>=1.3.0)
